MANIFEST.in
README
local-dev.sh
setup.py
bin/demand_server
serverondemand/__init__.py
serverondemand/demand.py
serverondemand/executor.py
serverondemand/xen.py
serverondemand.egg-info/PKG-INFO
serverondemand.egg-info/SOURCES.txt
serverondemand.egg-info/dependency_links.txt
serverondemand.egg-info/requires.txt
serverondemand.egg-info/top_level.txt
serverondemand/resources/bootstrap.sh
serverondemand/resources/demand_done.py