Metadata-Version: 1.0
Name: serverondemand
Version: 0.0.2
Summary: Wrapper library / script to run things on a as-needed server.
Home-page: https://github.com/adregner/server-on-demand
Author: Andrew Regner
Author-email: andrew@aregner.com
License: UNKNOWN
Platform: UNKNOWN
